ula/ula_control.v
module ula_control (
    input wire [1:0] ALUOp,
    input wire [2:0] funct3,
    input wire [6:0] funct7,
    output reg [3:0] ula_op
);

always @(*) begin
    case (ALUOp)
        2'b00: begin  // lw e sw
            ula_op = 4'b0010;  // ADD (calcular endereço)
        end
        2'b01: begin  // beq
            ula_op = 4'b0110;  // SUB (comparação)
        end
        2'b10: begin  // R-Format
            case ({funct7, funct3})
                10'b0000000_000: ula_op = 4'b0010;  // add
                10'b0100000_000: ula_op = 4'b0110;  // sub
                10'b0000000_111: ula_op = 4'b0000;  // and
                10'b0000000_110: ula_op = 4'b0001;  // or
                default:         ula_op = 4'bxxxx;  // inválido
            endcase
        end
        default: begin
            ula_op = 4'bxxxx;  // inválido
        end
    endcase
end

endmodule

ula/ula_control_tb.v
`timescale 1ps/1ps
`include "ula_control.v"

module ula_control_tb;

    // Sinais de entrada
    reg [1:0] ALUOp;
    reg [2:0] funct3;
    reg [6:0] funct7;

    // Sinal de saída
    wire [3:0] ula_op;

    // Instanciação do módulo a ser testado
    ula_control uut (
        .ALUOp(ALUOp),
        .funct3(funct3),
        .funct7(funct7),
        .ula_op(ula_op)
    );

    // Bloco inicial para simulação
    initial begin
        $dumpfile("ula_control_tb.vcd");  // Arquivo para visualização no GTKWAVE
        $dumpvars(0, ula_control_tb);     // Variáveis a serem dumpadas

        // Teste 1: lw/sw (ALUOp = 00)
        ALUOp = 2'b00; funct3 = 3'b000; funct7 = 7'b0000000;
        #20;
        $display("Teste 1 - ALUOp=%b, funct3=%b, funct7=%b, ula_op=%b", ALUOp, funct3, funct7, ula_op);

        // Teste 2: beq (ALUOp = 01)
        ALUOp = 2'b01; funct3 = 3'b000; funct7 = 7'b0000000;
        #20;
        $display("Teste 2 - ALUOp=%b, funct3=%b, funct7=%b, ula_op=%b", ALUOp, funct3, funct7, ula_op);

        // Teste 3: add (R-Format, ALUOp = 10)
        ALUOp = 2'b10; funct3 = 3'b000; funct7 = 7'b0000000;
        #20;
        $display("Teste 3 - ALUOp=%b, funct3=%b, funct7=%b, ula_op=%b", ALUOp, funct3, funct7, ula_op);

        // Teste 4: sub (R-Format, ALUOp = 10)
        ALUOp = 2'b10; funct3 = 3'b000; funct7 = 7'b0100000;
        #20;
        $display("Teste 4 - ALUOp=%b, funct3=%b, funct7=%b, ula_op=%b", ALUOp, funct3, funct7, ula_op);

        // Teste 5: and (R-Format, ALUOp = 10)
        ALUOp = 2'b10; funct3 = 3'b111; funct7 = 7'b0000000;
        #20;
        $display("Teste 5 - ALUOp=%b, funct3=%b, funct7=%b, ula_op=%b", ALUOp, funct3, funct7, ula_op);

        // Teste 6: or (R-Format, ALUOp = 10)
        ALUOp = 2'b10; funct3 = 3'b110; funct7 = 7'b0000000;
        #20;
        $display("Teste 6 - ALUOp=%b, funct3=%b, funct7=%b, ula_op=%b", ALUOp, funct3, funct7, ula_op);

        // Teste 7: Caso inválido (R-Format com funct inválido)
        ALUOp = 2'b10; funct3 = 3'b001; funct7 = 7'b0000000;
        #20;
        $display("Teste 7 - ALUOp=%b, funct3=%b, funct7=%b, ula_op=%b", ALUOp, funct3, funct7, ula_op);

        // Teste 8: ALUOp inválido
        ALUOp = 2'b11; funct3 = 3'b000; funct7 = 7'b0000000;
        #20;
        $display("Teste 8 - ALUOp=%b, funct3=%b, funct7=%b, ula_op=%b", ALUOp, funct3, funct7, ula_op);

        #20;
        $display("Teste Completo");
        $finish;
    end

endmodule

ula/ula_control_tb.vcd
$date
	Sun Jun 08 18:46:53 2025
$end
$version
	Icarus Verilog
$end
$timescale
	1ps
$end
$scope module ula_control_tb $end
$var wire 4 ! ula_op [3:0] $end
$var reg 2 " ALUOp [1:0] $end
$var reg 3 # funct3 [2:0] $end
$var reg 7 $ funct7 [6:0] $end
$scope module uut $end
$var wire 2 % ALUOp [1:0] $end
$var wire 3 & funct3 [2:0] $end
$var wire 7 ' funct7 [6:0] $end
$var reg 4 ( ula_op [3:0] $end
$upscope $end
$upscope $end
$enddefinitions $end
$comment Show the parameter values. $end
$dumpall
$end
#0
$dumpvars
b10 (
b0 '
b0 &
b0 %
b0 $
b0 #
b0 "
b10 !
$end
#20
b110 !
b110 (
b1 "
b1 %
#40
b10 !
b10 (
b10 "
b10 %
#60
b110 !
b110 (
b100000 $
b100000 '
#80
b0 !
b0 (
b0 $
b0 '
b111 #
b111 &
#100
b1 !
b1 (
b110 #
b110 &
#120
bx !
bx (
b1 #
b1 &
#140
b0 #
b0 &
b11 "
b11 %
