blocos_auxiliares/mux/mux.v
module mux(
    input [31:0] data_input_0,    // Primeira entrada de 32 bits
    input [31:0] data_input_1,    // Segunda entrada de 32 bits
    input select_signal,           // Sinal de seleção de 1 bit
    output reg [31:0] out_selected_data // Saída de 32 bits
);

    always @(*) begin
        if (select_signal == 1'b0) begin
            out_selected_data = data_input_0;    
        end else begin
            out_selected_data = data_input_1;    
        end
    end

endmodule

memoria/modulo_dados/memoria_dados.v
module memoria_dados(rs, wd, wr, rd);

    input [31:0] rs;        // Endereco de 32 bits para acessar a memoria
    input [31:0] wd;        // Dado de 32 bits a ser escrito
    input wr;               // Sinal de controle para escrita
    output reg [31:0] rd;   // Dado de 32 bits lido da memoria

    reg [31:0] memoria [0:1023]; // Memoria de 1024 palavras de 32 bits

    initial begin
        memoria[0] = 32'd0;   // Inicializa alguns enderecos como exemplo
        memoria[1] = 32'd100;
        memoria[2] = 32'hA5A5;
    end

    always @(*) begin
        if (wr) begin
            memoria[rs[9:0]] = wd; // Escrita quando wr = 1
        end
        rd = memoria[rs[9:0]]; // Leitura sempre reflete o valor atual
    end

endmodule

ula/ula.v
module ula (A, B, UlaOp, Out);

input [31:0]A, B;
input [0:3] UlaOp;
output reg [31:0]Out;

always @(*) begin
    case (UlaOp)
    4'b0000: Out <= A & B;
    4'b0001: Out <= A | B;
    4'b0010: Out <= A + B;
    4'b0110: Out <= A - B;
    default: Out <= 32'bz;
    endcase
end
endmodule

ula/ula_control.v
module ula_control (
    input wire [1:0] ALUOp,
    input wire [2:0] funct3,
    input wire [6:0] funct7,
    output reg [3:0] ula_op
);

always @(*) begin
    case (ALUOp)
        2'b00: begin  // lw e sw
            ula_op = 4'b0010;  // ADD (calcular endereço)
        end
        2'b01: begin  // beq
            ula_op = 4'b0110;  // SUB (comparação)
        end
        2'b10: begin  // R-Format
            case ({funct7, funct3})
                10'b0000000_000: ula_op = 4'b0010;  // add
                10'b0100000_000: ula_op = 4'b0110;  // sub
                10'b0000000_111: ula_op = 4'b0000;  // and
                10'b0000000_110: ula_op = 4'b0001;  // or
                default:         ula_op = 4'bxxxx;  // inválido
            endcase
        end
        default: begin
            ula_op = 4'bxxxx;  // inválido
        end
    endcase
end

endmodule

blocos_auxiliares/gerador_imediato/gerador_imediato.v
module gerador_imediato(
    input [31:0] instruction,    // Instrução completa de 32 bits
    output reg [31:0] immediate  // Valor imediato de 32 bits gerado
);

wire [6:0] opcode;
assign opcode = instruction[6:0];

always @(*) begin
    case (opcode)
        7'b0010011, // I-type (addi)
        7'b0000011, // lw
        7'b1100111: // jalr
            immediate = {{20{instruction[31]}}, instruction[31:20]};

        7'b0100011: // S-type (sw)
            immediate = {{20{instruction[31]}}, instruction[31:25], instruction[11:7]};

        7'b1100011: // B-type (beq)
            immediate = {{20{instruction[31]}}, instruction[7], instruction[30:25], instruction[11:8], 1'b0};

        default:
            immediate = 32'b0;
    endcase
end

endmodule

memoria/modulo_registradores/memoria_registradores.v
module registradores(rs1, rs2, rd, write_data, wr, read1, read2);

    input [4:0] rs1;          // Endereço do primeiro registrador a ser lido
    input [4:0] rs2;          // Endereço do segundo registrador a ser lido
    input [4:0] rd;           // Endereço do registrador a receber o dado escrito
    input [31:0] write_data;  // Dado a ser escrito
    input wr;                 // Sinal de controle para escrita
    output reg [31:0] read1;  // Valor lido do primeiro registrador
    output reg [31:0] read2;  // Valor lido do segundo registrador

    reg [31:0] regs [0:31];   // Banco de 32 registradores de 32 bits

    initial begin
        regs[0] = 32'd0;  // Inicializa o registrador 0 como zero
        regs[1] = 32'd10; // Inicializa outros registradores com valores
        regs[2] = 32'd20;
        regs[3] = 32'd30;
    end

    always @(*) begin
        read1 = regs[rs1];       // Leitura do primeiro registrador
        read2 = regs[rs2];       // Leitura do segundo registrador
        if (wr) begin
            regs[rd] = write_data; // Escrita no registrador se wr for ativo
        end
    end

endmodule

unidade_controle/unidade_controle.v
module controle(
    input [6:0] opcode,
    output reg ALUSrc,
    output reg PCSrc,
    output reg MemRead,
    output reg MemWrite,
    output reg RegWrite,
    output reg MemtoReg,
    output reg Branch,  
    output reg [1:0] ALUOp
);

always @(*) begin
    case (opcode)
        7'b0110011: begin  // Type R (add)
            ALUSrc = 0;
            PCSrc = 0;
            MemRead = 0;
            MemWrite = 0;
            RegWrite = 1;
            MemtoReg = 0;
            Branch = 0;
            ALUOp = 2'b10;
        end
        7'b0000011: begin  // lw
            ALUSrc = 1;
            PCSrc = 0;
            MemRead = 1;
            MemWrite = 0;
            RegWrite = 1;
            MemtoReg = 1;
            Branch = 0;
            ALUOp = 2'b00;
        end
        7'b0100011: begin  // sw
            ALUSrc = 1;
            PCSrc = 0;
            MemRead = 0;
            MemWrite = 1;
            RegWrite = 0;
            MemtoReg = 0;  // Não importa (X)
            Branch = 0;
            ALUOp = 2'b00;
        end
        7'b1100011: begin  // beq
            ALUSrc = 0;
            PCSrc = 1;
            MemRead = 0;
            MemWrite = 0;
            RegWrite = 0;
            MemtoReg = 0;  // Não importa (X)
            Branch = 1;
            ALUOp = 2'b01;
        end
        default: begin  // Caso inválido
            ALUSrc = 0;
            PCSrc = 0;
            MemRead = 0;
            MemWrite = 0;
            RegWrite = 0;
            MemtoReg = 0;
            Branch = 0;
            ALUOp = 2'b00;
        end
    endcase
end

endmodule

memoria/modulo_instrucao/memoria_instrucao.v
module memoria_instrucao(endereco, dado);

    input [7:0] endereco; // entrada (index por palavra de 32 bits)
    output reg [31:0] dado; // saida

    reg [31:0] memoria [0:255]; // 256 instrucoes de 32 bits

    initial begin
        // lw x1, 0(x0)       # x1 = Mem[0]
        memoria[0] = 32'b0000000_00000_00000_010_00001_0000011;

        // sw x1, 0(x0)       # Mem[0] = x1
        memoria[1] = 32'b0000000_00001_00000_010_00000_0100011;

        // add x2, x1, x1     # x2 = x1 + x1 (deve ser 10 se x1 = 5)
        memoria[2] = 32'b0000000_00001_00001_000_00010_0110011;

        // beq x2, x1, 4      # se x2 == x1, salta +4 bytes (1 instrucao)
        memoria[3] = 32'b0000000_00001_00010_000_00001_1100011;

        // nop (add x0, x0, x0)
        memoria[4] = 32'b0000000_00000_00000_000_00000_0110011;
    end 

    always @(*) begin
        dado = memoria[endereco]; // leitura
    end

endmodule

datapath/datapath.v
module datapath (
    input wire clk,
    input wire reset,
    output wire [31:0] pc_atual
);

    // Registradores e fios
    reg [31:0] pc;                        // Registrador do PC
    wire [31:0] instrucao;                // Instrução lida da memória
    wire [6:0] opcode;                    // Opcode da instrução
    wire [4:0] rs1, rs2, rd;              // Endereços dos registradores
    wire [2:0] funct3;                    // Campo funct3 da instrução
    wire [6:0] funct7;                    // Campo funct7 da instrução
    wire [31:0] dado_reg1, dado_reg2;     // Dados lidos dos registradores
    wire [31:0] imediato;                 // Valor imediato gerado
    wire [31:0] operando_ula;             // Segundo operando da ULA (saída do mux)
    wire [31:0] resultado_ula;            // Resultado da ULA
    wire [31:0] dado_memoria;             // Dado lido da memória
    wire [31:0] dado_escrita;             // Dado a ser escrito nos registradores

    // Sinais de controle
    wire reg_escrita, mem_escrita, alu_src, mem_para_reg, branch;
    wire [1:0] alu_op;
    wire [3:0] operacao_ula;
    wire pc_src;

    
    memoria_instrucao mem_instrucao (
        .endereco(pc[7:2]),              // Usa os 6 bits menos significativos
        .dado(instrucao)
    );

    
    assign opcode  = instrucao[6:0];
    assign rd      = instrucao[11:7];
    assign funct3  = instrucao[14:12];
    assign rs1     = instrucao[19:15];
    assign rs2     = instrucao[24:20];
    assign funct7  = instrucao[31:25];

    controle unidade_controle (
        .opcode(opcode),
        .ALUSrc(alu_src),
        .PCSrc(pc_src),
        .MemRead(reg_escrita),           
        .MemWrite(mem_escrita),
        .RegWrite(reg_escrita),          
        .MemtoReg(mem_para_reg),
        .Branch(branch),
        .ALUOp(alu_op)
    );

    registradores banco_registradores (
        .rs1(rs1),
        .rs2(rs2),
        .rd(rd),
        .write_data(dado_escrita),
        .wr(reg_escrita),
        .read1(dado_reg1),
        .read2(dado_reg2)
    );

    gerador_imediato gerador_imediato (
        .instruction(instrucao),
        .immediate(imediato)
    );

    mux mux_alu (
        .data_input_0(dado_reg2),
        .data_input_1(imediato),
        .select_signal(alu_src),
        .out_selected_data(operando_ula)
    );

    ula_control controle_ula (
        .ALUOp(alu_op),
        .funct3(funct3),
        .funct7(funct7),
        .ula_op(operacao_ula)
    );

    ula unidade_ula (
        .A(dado_reg1),
        .B(operando_ula),
        .UlaOp(operacao_ula),
        .Out(resultado_ula)
    );

    memoria_dados mem_dados (
        .rs(resultado_ula),
        .wd(dado_reg2),
        .wr(mem_escrita),
        .rd(dado_memoria)
    );

    mux mux_escrita (
        .data_input_0(resultado_ula),
        .data_input_1(dado_memoria),
        .select_signal(mem_para_reg),
        .out_selected_data(dado_escrita)
    );

    // Lógica de atualização do PC
    wire [31:0] pc_mais_4 = pc + 4;
    wire [31:0] pc_branch = pc + imediato;
    wire branch_condicao = branch & (resultado_ula == 0);  // beq toma branch se igual
    wire proximo_pc = pc_src & branch_condicao;            // Usa PCSrc do diagrama
    assign pc_atual = proximo_pc ? pc_branch : pc_mais_4;

    // Atualização do PC com clock e reset
    always @(posedge clk or posedge reset) begin
        if (reset)
            pc <= 0;
        else
            pc <= pc_atual;
    end

endmodule

datapath/datapath_tb.v
module datapath_tb;

    reg clk, reset;
    wire [31:0] pc_atual;

    datapath dut (
        .clk(clk),
        .reset(reset),
        .pc_atual(pc_atual)
    );

    // Geração de clock (período de 10ps, alterna a cada 5ps)
    initial begin
        clk = 0;
        forever #5 clk = ~clk;
    end

    // Reset e execução
    initial begin
        reset = 1;
        #10;
        reset = 0;

        #100;  // Simulação por 100ps após o reset

        $finish;
    end

    // Exibe o PC final e garante o dump
    initial begin
        $dumpfile("datapath_tb.vcd");  // Especifica o arquivo .vcd
        $dumpvars(0, datapath_tb);     // Dump de todas as variáveis do módulo
        #110;  // Após 10ps de reset + 100ps de execução
        $display("PC final: %d", pc_atual);
    end

endmodule

datapath/datapath_tb.vcd
$date
	Mon Jun 09 01:34:48 2025
$end
$version
	Icarus Verilog
$end
$timescale
	1s
$end
$scope module datapath_tb $end
$var wire 32 ! pc_atual [31:0] $end
$var reg 1 " clk $end
$var reg 1 # reset $end
$scope module dut $end
$var wire 1 $ branch_condicao $end
$var wire 1 " clk $end
$var wire 1 % proximo_pc $end
$var wire 1 & reg_escrita $end
$var wire 1 # reset $end
$var wire 5 ' rs2 [4:0] $end
$var wire 5 ( rs1 [4:0] $end
$var wire 32 ) resultado_ula [31:0] $end
$var wire 5 * rd [4:0] $end
$var wire 1 + pc_src $end
$var wire 32 , pc_mais_4 [31:0] $end
$var wire 32 - pc_branch [31:0] $end
$var wire 32 . pc_atual [31:0] $end
$var wire 32 / operando_ula [31:0] $end
$var wire 4 0 operacao_ula [3:0] $end
$var wire 7 1 opcode [6:0] $end
$var wire 1 2 mem_para_reg $end
$var wire 1 3 mem_escrita $end
$var wire 32 4 instrucao [31:0] $end
$var wire 32 5 imediato [31:0] $end
$var wire 7 6 funct7 [6:0] $end
$var wire 3 7 funct3 [2:0] $end
$var wire 32 8 dado_reg2 [31:0] $end
$var wire 32 9 dado_reg1 [31:0] $end
$var wire 32 : dado_memoria [31:0] $end
$var wire 32 ; dado_escrita [31:0] $end
$var wire 1 < branch $end
$var wire 1 = alu_src $end
$var wire 2 > alu_op [1:0] $end
$var reg 32 ? pc [31:0] $end
$scope module banco_registradores $end
$var wire 5 @ rd [4:0] $end
$var wire 5 A rs1 [4:0] $end
$var wire 5 B rs2 [4:0] $end
$var wire 1 & wr $end
$var wire 32 C write_data [31:0] $end
$var reg 32 D read1 [31:0] $end
$var reg 32 E read2 [31:0] $end
$upscope $end
$scope module controle_ula $end
$var wire 3 F funct3 [2:0] $end
$var wire 7 G funct7 [6:0] $end
$var wire 2 H ALUOp [1:0] $end
$var reg 4 I ula_op [3:0] $end
$upscope $end
$scope module gerador_imediato $end
$var wire 7 J opcode [6:0] $end
$var wire 32 K instruction [31:0] $end
$var reg 32 L immediate [31:0] $end
$upscope $end
$scope module mem_dados $end
$var wire 32 M wd [31:0] $end
$var wire 1 3 wr $end
$var wire 32 N rs [31:0] $end
$var reg 32 O rd [31:0] $end
$upscope $end
$scope module mem_instrucao $end
$var wire 8 P endereco [7:0] $end
$var reg 32 Q dado [31:0] $end
$upscope $end
$scope module mux_alu $end
$var wire 32 R data_input_0 [31:0] $end
$var wire 32 S data_input_1 [31:0] $end
$var wire 1 = select_signal $end
$var reg 32 T out_selected_data [31:0] $end
$upscope $end
$scope module mux_escrita $end
$var wire 32 U data_input_1 [31:0] $end
$var wire 1 2 select_signal $end
$var wire 32 V data_input_0 [31:0] $end
$var reg 32 W out_selected_data [31:0] $end
$upscope $end
$scope module unidade_controle $end
$var wire 7 X opcode [6:0] $end
$var reg 2 Y ALUOp [1:0] $end
$var reg 1 = ALUSrc $end
$var reg 1 < Branch $end
$var reg 1 Z MemRead $end
$var reg 1 3 MemWrite $end
$var reg 1 2 MemtoReg $end
$var reg 1 + PCSrc $end
$var reg 1 [ RegWrite $end
$upscope $end
$scope module unidade_ula $end
$var wire 32 \ A [31:0] $end
$var wire 32 ] B [31:0] $end
$var wire 4 ^ UlaOp [0:3] $end
$var reg 32 _ Out [31:0] $end
$upscope $end
$upscope $end
$upscope $end
$enddefinitions $end
$comment Show the parameter values. $end
$dumpall
$end
#0
$dumpvars
b0 _
b10 ^
b0 ]
b0 \
1[
1Z
b0 Y
b11 X
b0 W
b0 V
b0 U
b0 T
b0 S
b0 R
b10000010000011 Q
b0 P
b0 O
b0 N
b0 M
b0 L
b10000010000011 K
b11 J
b10 I
b0 H
b0 G
b10 F
b0 E
b0 D
b0 C
b0 B
b0 A
b1 @
b0 ?
b0 >
1=
0<
b0 ;
b0 :
b0 9
b0 8
b10 7
b0 6
b0 5
b10000010000011 4
03
12
b11 1
b10 0
b0 /
b100 .
b0 -
b100 ,
0+
b1 *
b0 )
b0 (
b0 '
1&
0%
0$
1#
0"
b100 !
$end
#5
1"
#10
0"
0#
#15
b0 )
b0 N
b0 V
b0 _
02
0[
13
0&
0Z
b0 /
b0 T
b0 ]
b100011 J
b1 '
b1 B
b0 *
b0 @
b100011 1
b100011 X
b0 5
b0 L
b0 S
b100000010000000100011 4
b100000010000000100011 K
b100000010000000100011 Q
b1 P
b1000 !
b1000 .
b1000 ,
b100 -
b100 ?
1"
#20
0"
#25
b0 )
b0 N
b0 V
b0 _
b10 >
b10 H
b10 Y
x&
1[
03
0=
b0 /
b0 T
b0 ]
b110011 J
b1 (
b1 A
b0 7
b0 F
b10 *
b10 @
b110011 1
b110011 X
b0 5
b0 L
b0 S
b100001000000100110011 4
b100001000000100110011 K
b100001000000100110011 Q
b10 P
b1100 !
b1100 .
b1100 ,
b1000 -
b1000 ?
1"
#30
0"
#35
bx :
bx O
bx U
b10100 ;
b10100 C
b10100 W
b10100 )
b10100 N
b10100 V
b10100 _
0%
b110 0
b110 I
b110 ^
0$
b100000000000 5
b100000000000 L
b100000000000 S
b10100 9
b10100 D
b10100 \
b1 >
b1 H
b1 Y
1<
0&
0[
1+
b1100011 J
b10 (
b10 A
b1 *
b1 @
b1100011 1
b1100011 X
b100010000000011100011 4
b100010000000011100011 K
b100010000000011100011 Q
b11 P
b10000 !
b10000 .
b10000 ,
b100000001100 -
b1100 ?
1"
#40
0"
#45
b0 :
b0 O
b0 U
b0 ;
b0 C
b0 W
b0 )
b0 N
b0 V
b0 _
b10 0
b10 I
b10 ^
b0 9
b0 D
b0 \
b10 >
b10 H
b10 Y
0<
x&
1[
0+
b110011 J
b0 '
b0 B
b0 (
b0 A
b0 *
b0 @
b110011 1
b110011 X
b0 5
b0 L
b0 S
b110011 4
b110011 K
b110011 Q
b100 P
b10100 !
b10100 .
b10100 ,
b10000 -
b10000 ?
1"
#50
0"
#55
bx :
bx O
bx U
bx ;
bx C
bx W
bx )
bx N
bx V
bx _
bx /
bx T
bx ]
bx 8
bx E
bx M
bx R
bx 9
bx D
bx \
b0 >
b0 H
b0 Y
0&
0[
bx J
bx 6
bx G
bx '
bx B
bx (
bx A
bx 7
bx F
bx *
bx @
bx 1
bx X
bx 4
bx K
bx Q
b101 P
b11000 !
b11000 .
b11000 ,
b10100 -
b10100 ?
1"
#60
0"
#65
b110 P
b11100 !
b11100 .
b11100 ,
b11000 -
b11000 ?
1"
#70
0"
#75
b111 P
b100000 !
b100000 .
b100000 ,
b11100 -
b11100 ?
1"
#80
0"
#85
b1000 P
b100100 !
b100100 .
b100100 ,
b100000 -
b100000 ?
1"
#90
0"
#95
b1001 P
b101000 !
b101000 .
b101000 ,
b100100 -
b100100 ?
1"
#100
0"
#105
b1010 P
b101100 !
b101100 .
b101100 ,
b101000 -
b101000 ?
1"
