memoria/modulo_dados/memoria_dados.v
module memoria_dados(rs, wd, wr, rd);

    input [31:0] rs;        // Endereco de 32 bits para acessar a memoria
    input [31:0] wd;        // Dado de 32 bits a ser escrito
    input wr;               // Sinal de controle para escrita
    output reg [31:0] rd;   // Dado de 32 bits lido da memoria

    reg [31:0] memoria [0:1023]; // Memoria de 1024 palavras de 32 bits

    initial begin
        memoria[0] = 32'd0;   // Inicializa alguns enderecos como exemplo
        memoria[1] = 32'd100;
        memoria[2] = 32'hA5A5;
    end

    always @(*) begin
        if (wr) begin
            memoria[rs[9:0]] = wd; // Escrita quando wr = 1
        end
        rd = memoria[rs[9:0]]; // Leitura sempre reflete o valor atual
    end

endmodule

ula/ula.v
module ula (A, B, UlaOp, Out);

input [31:0]A, B;
input [0:3] UlaOp;
output reg [31:0]Out;

always @(*) begin
    case (UlaOp)
    4'b0000: Out <= A & B;
    4'b0001: Out <= A | B;
    4'b0010: Out <= A + B;
    4'b0110: Out <= A - B;
    default: Out <= 32'bz;
    endcase
end
endmodule

ula/ula_control.v
module ula_control (
    input wire [1:0] ALUOp,
    input wire [2:0] funct3,
    input wire [6:0] funct7,
    output reg [3:0] ula_op
);

always @(*) begin
    case (ALUOp)
        2'b00: begin  // lw e sw
            ula_op = 4'b0010;  // ADD (calcular endereço)
        end
        2'b01: begin  // beq
            ula_op = 4'b0110;  // SUB (comparação)
        end
        2'b10: begin  // R-Format
            case ({funct7, funct3})
                10'b0000000_000: ula_op = 4'b0010;  // add
                10'b0100000_000: ula_op = 4'b0110;  // sub
                10'b0000000_111: ula_op = 4'b0000;  // and
                10'b0000000_110: ula_op = 4'b0001;  // or
                default:         ula_op = 4'bxxxx;  // inválido
            endcase
        end
        default: begin
            ula_op = 4'bxxxx;  // inválido
        end
    endcase
end

endmodule

blocos_auxiliares/gerador_imediato/gerador_imediato.v
module gerador_imediato(
    input [31:0] instruction,    // Instrução completa de 32 bits
    output reg [31:0] immediate  // Valor imediato de 32 bits gerado
);

wire [6:0] opcode;
assign opcode = instruction[6:0];

always @(*) begin
    case (opcode)
        7'b0010011, // I-type (addi)
        7'b0000011, // lw
        7'b1100111: // jalr
            immediate = {{20{instruction[31]}}, instruction[31:20]};

        7'b0100011: // S-type (sw)
            immediate = {{20{instruction[31]}}, instruction[31:25], instruction[11:7]};

        7'b1100011: // B-type (beq)
            immediate = {{20{instruction[31]}}, instruction[7], instruction[30:25], instruction[11:8], 1'b0};

        default:
            immediate = 32'b0;
    endcase
end

endmodule

memoria/modulo_registradores/memoria_registradores.v
module registradores(rs1, rs2, rd, write_data, wr, read1, read2);

    input [4:0] rs1;          // Endereço do primeiro registrador a ser lido
    input [4:0] rs2;          // Endereço do segundo registrador a ser lido
    input [4:0] rd;           // Endereço do registrador a receber o dado escrito
    input [31:0] write_data;  // Dado a ser escrito
    input wr;                 // Sinal de controle para escrita
    output reg [31:0] read1;  // Valor lido do primeiro registrador
    output reg [31:0] read2;  // Valor lido do segundo registrador

    reg [31:0] regs [0:31];   // Banco de 32 registradores de 32 bits

    initial begin
        regs[0] = 32'd0;  // Inicializa o registrador 0 como zero
        regs[1] = 32'd10; // Inicializa outros registradores com valores
        regs[2] = 32'd20;
        regs[3] = 32'd30;
    end

    always @(*) begin
        read1 = regs[rs1];       // Leitura do primeiro registrador
        read2 = regs[rs2];       // Leitura do segundo registrador
        if (wr) begin
            regs[rd] = write_data; // Escrita no registrador se wr for ativo
        end
    end

endmodule

unidade_controle/unidade_controle.v
module controle(
    input [6:0] opcode,
    output reg ALUSrc,
    output reg PCSrc,
    output reg MemRead,
    output reg MemWrite,
    output reg RegWrite,
    output reg MemtoReg,
    output reg Branch,  
    output reg [1:0] ALUOp
);

always @(*) begin
    case (opcode)
        7'b0110011: begin  // Type R (add)
            ALUSrc = 0;
            PCSrc = 0;
            MemRead = 0;
            MemWrite = 0;
            RegWrite = 1;
            MemtoReg = 0;
            Branch = 0;
            ALUOp = 2'b10;
        end
        7'b0000011: begin  // lw
            ALUSrc = 1;
            PCSrc = 0;
            MemRead = 1;
            MemWrite = 0;
            RegWrite = 1;
            MemtoReg = 1;
            Branch = 0;
            ALUOp = 2'b00;
        end
        7'b0100011: begin  // sw
            ALUSrc = 1;
            PCSrc = 0;
            MemRead = 0;
            MemWrite = 1;
            RegWrite = 0;
            MemtoReg = 0;  // Não importa (X)
            Branch = 0;
            ALUOp = 2'b00;
        end
        7'b1100011: begin  // beq
            ALUSrc = 0;
            PCSrc = 1;
            MemRead = 0;
            MemWrite = 0;
            RegWrite = 0;
            MemtoReg = 0;  // Não importa (X)
            Branch = 1;
            ALUOp = 2'b01;
        end
        default: begin  // Caso inválido
            ALUSrc = 0;
            PCSrc = 0;
            MemRead = 0;
            MemWrite = 0;
            RegWrite = 0;
            MemtoReg = 0;
            Branch = 0;
            ALUOp = 2'b00;
        end
    endcase
end

endmodule

memoria/modulo_instrucao/memoria_instrucao.v
module memoria_instrucao(endereco, dado);

    input [7:0] endereco; // entrada (index por palavra de 32 bits)
    output reg [31:0] dado; // saida

    reg [31:0] memoria [0:255]; // 256 instrucoes de 32 bits

    initial begin
        // lw x1, 0(x0)       # x1 = Mem[0]
        memoria[0] = 32'b0000000_00000_00000_010_00001_0000011;

        // sw x1, 0(x0)       # Mem[0] = x1
        memoria[1] = 32'b0000000_00001_00000_010_00000_0100011;

        // add x2, x1, x1     # x2 = x1 + x1 (deve ser 10 se x1 = 5)
        memoria[2] = 32'b0000000_00001_00001_000_00010_0110011;

        // beq x2, x1, 4      # se x2 == x1, salta +4 bytes (1 instrucao)
        memoria[3] = 32'b0000000_00001_00010_000_00001_1100011;

        // nop (add x0, x0, x0)
        memoria[4] = 32'b0000000_00000_00000_000_00000_0110011;
    end 

    always @(*) begin
        dado = memoria[endereco]; // leitura
    end

endmodule

datapath/datapath.v
module datapath(
    input  wire        clk,
    input  wire        reset,
    output wire [31:0] pc_atual,
    // sinais para debug
    output wire [31:0] instrucao,
    output wire [31:0] dado_reg1,
    output wire [31:0] dado_reg2,
    output wire [31:0] resultado_ula,
    output wire [31:0] dado_memoria,
    output wire [31:0] dado_escrita
);

    // PC
    reg  [31:0] pc;
    wire [31:0] pc_plus4, pc_branch, pc_next;
    wire [7:0]  endereco_instr = pc[9:2];

    // Fetch
    memoria_instrucao mem_instrucao(
        .endereco(endereco_instr),
        .dado     (instrucao)
    );

    // Decode fields
    wire [6:0] opcode   = instrucao[6:0];
    wire [4:0] rd       = instrucao[11:7];
    wire [2:0] funct3   = instrucao[14:12];
    wire [4:0] rs1      = instrucao[19:15];
    wire [4:0] rs2      = instrucao[24:20];
    wire [6:0] funct7   = instrucao[31:25];

    // Controle
    wire        ALUSrc, PCSrc, MemRead, MemWrite, RegWrite, MemtoReg, Branch;
    wire [1:0]  ALUOp;
    controle ucont (
        .opcode   (opcode),
        .ALUSrc   (ALUSrc),
        .PCSrc    (PCSrc),
        .MemRead  (MemRead),
        .MemWrite (MemWrite),
        .RegWrite (RegWrite),
        .MemtoReg (MemtoReg),
        .Branch   (Branch),
        .ALUOp    (ALUOp)
    );

    // Banco de registradores
    registradores regs(
        .rs1       (rs1),
        .rs2       (rs2),
        .rd        (rd),
        .write_data(dado_escrita),
        .wr        (RegWrite),
        .read1     (dado_reg1),
        .read2     (dado_reg2)
    );

    // Gerador de imediato
    wire [31:0] immediate;
    gerador_imediato gen_imm(
        .instruction(instrucao),
        .immediate (immediate)
    );

    // Controle da ULA
    wire [3:0] ula_op;
    ula_control controle_ula(
        .ALUOp  (ALUOp),
        .funct3 (funct3),
        .funct7 (funct7),
        .ula_op (ula_op)
    );

    // Mux de segundo operando da ULA
    wire [31:0] operando_b = ALUSrc ? immediate : dado_reg2;

    // ULA
    ula unidade_ula(
        .A    (dado_reg1),
        .B    (operando_b),
        .UlaOp(ula_op),
        .Out  (resultado_ula)
    );

    // Memória de dados
    memoria_dados mem_data(
        .rs(resultado_ula),
        .wd(dado_reg2),
        .wr(MemWrite),
        .rd(dado_memoria)
    );

    // Mux de write‐back
    assign dado_escrita = MemtoReg ? dado_memoria : resultado_ula;

    // Cálculo de próximo PC
    assign pc_plus4  = pc + 32'd4;
    assign pc_branch = pc + immediate;
    wire branch_taken = Branch && (resultado_ula == 32'd0);
    assign pc_next   = branch_taken ? pc_branch : pc_plus4;

    // Atualização de PC
    always @(posedge clk or posedge reset) begin
        if (reset) pc <= 32'd0;
        else       pc <= pc_next;
    end

    assign pc_atual = pc;

endmodule

datapath/datapath_tb.v
`timescale 1ns/1ps

module datapath_tb;
    reg         clk   = 0;
    reg         reset = 1;
    wire [31:0] pc_atual, instrucao;
    wire [31:0] dado_reg1, dado_reg2;
    wire [31:0] resultado_ula, dado_memoria, dado_escrita;

    datapath dut (
        .clk           (clk),
        .reset         (reset),
        .pc_atual      (pc_atual),
        .instrucao     (instrucao),
        .dado_reg1     (dado_reg1),
        .dado_reg2     (dado_reg2),
        .resultado_ula (resultado_ula),
        .dado_memoria  (dado_memoria),
        .dado_escrita  (dado_escrita)
    );

    initial begin
 
        $dumpfile("datapath_tb.vcd");
        $dumpvars(0, datapath_tb);


        #10 reset = 0;
    end


    always #10 clk = ~clk;

    integer cycle = 0;
    always @(posedge clk) begin
        $display("CYCLE=%0d PC=%0d INST=0x%h R1=%0d R2=%0d ALU=%0d MEM=%0d WB=%0d",
                 cycle, pc_atual, instrucao,
                 dado_reg1, dado_reg2,
                 resultado_ula, dado_memoria, dado_escrita);
        cycle = cycle + 1;
        if (cycle == 8) $finish;
    end
endmodule

datapath/datapath_tb.vcd
$date
	Mon Jun 09 20:18:04 2025
$end
$version
	Icarus Verilog
$end
$timescale
	1ps
$end
$scope module datapath_tb $end
$var wire 32 ! resultado_ula [31:0] $end
$var wire 32 " pc_atual [31:0] $end
$var wire 32 # instrucao [31:0] $end
$var wire 32 $ dado_reg2 [31:0] $end
$var wire 32 % dado_reg1 [31:0] $end
$var wire 32 & dado_memoria [31:0] $end
$var wire 32 ' dado_escrita [31:0] $end
$var reg 1 ( clk $end
$var reg 1 ) reset $end
$var integer 32 * cycle [31:0] $end
$scope module dut $end
$var wire 1 + branch_taken $end
$var wire 1 ( clk $end
$var wire 32 , pc_atual [31:0] $end
$var wire 1 ) reset $end
$var wire 4 - ula_op [3:0] $end
$var wire 5 . rs2 [4:0] $end
$var wire 5 / rs1 [4:0] $end
$var wire 32 0 resultado_ula [31:0] $end
$var wire 5 1 rd [4:0] $end
$var wire 32 2 pc_plus4 [31:0] $end
$var wire 32 3 pc_next [31:0] $end
$var wire 32 4 pc_branch [31:0] $end
$var wire 32 5 operando_b [31:0] $end
$var wire 7 6 opcode [6:0] $end
$var wire 32 7 instrucao [31:0] $end
$var wire 32 8 immediate [31:0] $end
$var wire 7 9 funct7 [6:0] $end
$var wire 3 : funct3 [2:0] $end
$var wire 8 ; endereco_instr [7:0] $end
$var wire 32 < dado_reg2 [31:0] $end
$var wire 32 = dado_reg1 [31:0] $end
$var wire 32 > dado_memoria [31:0] $end
$var wire 32 ? dado_escrita [31:0] $end
$var wire 1 @ RegWrite $end
$var wire 1 A PCSrc $end
$var wire 1 B MemtoReg $end
$var wire 1 C MemWrite $end
$var wire 1 D MemRead $end
$var wire 1 E Branch $end
$var wire 1 F ALUSrc $end
$var wire 2 G ALUOp [1:0] $end
$var reg 32 H pc [31:0] $end
$scope module controle_ula $end
$var wire 3 I funct3 [2:0] $end
$var wire 7 J funct7 [6:0] $end
$var wire 2 K ALUOp [1:0] $end
$var reg 4 L ula_op [3:0] $end
$upscope $end
$scope module gen_imm $end
$var wire 7 M opcode [6:0] $end
$var wire 32 N instruction [31:0] $end
$var reg 32 O immediate [31:0] $end
$upscope $end
$scope module mem_data $end
$var wire 1 C wr $end
$var wire 32 P wd [31:0] $end
$var wire 32 Q rs [31:0] $end
$var reg 32 R rd [31:0] $end
$upscope $end
$scope module mem_instrucao $end
$var wire 8 S endereco [7:0] $end
$var reg 32 T dado [31:0] $end
$upscope $end
$scope module regs $end
$var wire 5 U rd [4:0] $end
$var wire 5 V rs1 [4:0] $end
$var wire 5 W rs2 [4:0] $end
$var wire 32 X write_data [31:0] $end
$var wire 1 @ wr $end
$var reg 32 Y read1 [31:0] $end
$var reg 32 Z read2 [31:0] $end
$upscope $end
$scope module ucont $end
$var wire 7 [ opcode [6:0] $end
$var reg 2 \ ALUOp [1:0] $end
$var reg 1 F ALUSrc $end
$var reg 1 E Branch $end
$var reg 1 D MemRead $end
$var reg 1 C MemWrite $end
$var reg 1 B MemtoReg $end
$var reg 1 A PCSrc $end
$var reg 1 @ RegWrite $end
$upscope $end
$scope module unidade_ula $end
$var wire 32 ] A [31:0] $end
$var wire 32 ^ B [31:0] $end
$var wire 4 _ UlaOp [0:3] $end
$var reg 32 ` Out [31:0] $end
$upscope $end
$upscope $end
$upscope $end
$enddefinitions $end
$comment Show the parameter values. $end
$dumpall
$end
#0
$dumpvars
b0 `
b10 _
b0 ^
b0 ]
b0 \
b11 [
b0 Z
b0 Y
b0 X
b0 W
b0 V
b1 U
b10000010000011 T
b0 S
b0 R
b0 Q
b0 P
b0 O
b10000010000011 N
b11 M
b10 L
b0 K
b0 J
b10 I
b0 H
b0 G
1F
0E
1D
0C
1B
0A
1@
b0 ?
b0 >
b0 =
b0 <
b0 ;
b10 :
b0 9
b0 8
b10000010000011 7
b11 6
b0 5
b0 4
b100 3
b100 2
b1 1
b0 0
b0 /
b0 .
b10 -
b0 ,
0+
b0 *
1)
0(
b0 '
b0 &
b0 %
b0 $
b10000010000011 #
b0 "
b0 !
$end
#10000
b0 !
b0 0
b0 Q
b0 `
0B
0@
1C
0D
b0 5
b0 ^
b100011 M
b1 .
b1 W
b0 1
b0 U
b100011 6
b100011 [
b0 8
b0 O
b100000010000000100011 #
b100000010000000100011 7
b100000010000000100011 N
b100000010000000100011 T
b1 ;
b1 S
b1000 3
b1000 2
b100 4
b100 "
b100 ,
b100 H
b1 *
1(
0)
#20000
0(
#30000
b0 !
b0 0
b0 Q
b0 `
b10 G
b10 K
b10 \
1@
0C
0F
b0 5
b0 ^
b110011 M
b1 /
b1 V
b0 :
b0 I
b10 1
b10 U
b110011 6
b110011 [
b0 8
b0 O
b100001000000100110011 #
b100001000000100110011 7
b100001000000100110011 N
b100001000000100110011 T
b10 ;
b10 S
b1100 3
b1100 2
b1000 4
b1000 "
b1000 ,
b1000 H
b10 *
1(
#40000
0(
#50000
b110 -
b110 L
b110 _
1+
b100000000000 8
b100000000000 O
b1 G
b1 K
b1 \
1E
0@
1A
b1100011 M
b10 /
b10 V
b1 1
b1 U
b1100011 6
b1100011 [
b100010000000011100011 #
b100010000000011100011 7
b100010000000011100011 N
b100010000000011100011 T
b11 ;
b11 S
b100000001100 3
b10000 2
b100000001100 4
b1100 "
b1100 ,
b1100 H
b11 *
1(
#60000
0(
#70000
b1000000001100 3
b100000010000 2
b1000000001100 4
b100000001100 "
b100000001100 ,
b100000001100 H
b100 *
1(
#80000
0(
#90000
b1100000001100 3
b1000000010000 2
b1100000001100 4
b1000000001100 "
b1000000001100 ,
b1000000001100 H
b101 *
1(
#100000
0(
#110000
b10000000001100 3
b1100000010000 2
b10000000001100 4
b1100000001100 "
b1100000001100 ,
b1100000001100 H
b110 *
1(
#120000
0(
#130000
b10100000001100 3
b10000000010000 2
b10100000001100 4
b10000000001100 "
b10000000001100 ,
b10000000001100 H
b111 *
1(
#140000
0(
#150000
b11000000001100 3
b10100000010000 2
b11000000001100 4
b10100000001100 "
b10100000001100 ,
b10100000001100 H
b1000 *
1(
